aws_key_formatter/__init__.py
aws_key_formatter/__main__.py
aws_key_formatter/__version__.py
aws_key_formatter/aws_key_formatter.py
aws_key_formatter/cli.py
aws_key_formatter-0.2.0.dist-info/LICENSE.md
aws_key_formatter-0.2.0.dist-info/METADATA
aws_key_formatter-0.2.0.dist-info/WHEEL
aws_key_formatter-0.2.0.dist-info/entry_points.txt
aws_key_formatter-0.2.0.dist-info/top_level.txt
aws_key_formatter-0.2.0.dist-info/RECORD
