Metadata-Version: 2.1
Name: aws-key-formatter
Version: 0.2.0
Summary: UNKNOWN
Home-page: https://github.com/KeltonKarboviak/aws-key-formatter
Author: Kelton Karboviak
Author-email: kelton.karboviak@gmail.com
License: MIT
Platform: UNKNOWN
Classifier: License :: OSI Approved :: MIT License
Classifier: Intended Audience :: Developers
Classifier: Programming Language :: Python :: 2
Classifier: Programming Language :: Python :: 2.7
Classifier: Programming Language :: Python :: 3
Classifier: Programming Language :: Python :: 3.6
Classifier: Programming Language :: Python :: 3.7
Classifier: Operating System :: OS Independent
Requires-Dist: boto3 (<2.0,>=1.9)
Requires-Dist: click (<8.0,>=7.0)
